PlasMAAG/__init__.py
PlasMAAG/__main__.py
PlasMAAG/click_file_types.py
PlasMAAG/command_line_runners.py
PlasMAAG/environment.py
PlasMAAG/richclick_options.py
PlasMAAG/snakefile.smk
PlasMAAG/envs/PlasMAAG.yaml
PlasMAAG/envs/genomad.yaml
PlasMAAG/envs/node2vec.yaml
PlasMAAG/envs/spades_env.yaml
PlasMAAG/envs/strobe_env.yaml
PlasMAAG/files_used_in_snakemake_workflow/__init__.py
PlasMAAG/files_used_in_snakemake_workflow/circularisation.py
PlasMAAG/files_used_in_snakemake_workflow/classify_bins_with_geNomad.py
PlasMAAG/files_used_in_snakemake_workflow/concatenate.py
PlasMAAG/files_used_in_snakemake_workflow/embeddings_to_neighs.py
PlasMAAG/files_used_in_snakemake_workflow/fastnode2vec_args.py
PlasMAAG/files_used_in_snakemake_workflow/git_commit.py
PlasMAAG/files_used_in_snakemake_workflow/merge_assembly_alignment_graphs.py
PlasMAAG/files_used_in_snakemake_workflow/merge_circular_plamb_clusters.py
PlasMAAG/files_used_in_snakemake_workflow/process_blastout.py
PlasMAAG/files_used_in_snakemake_workflow/process_gfa.py
PlasMAAG/files_used_in_snakemake_workflow/write_candidate_bins.py
vamb/__init__.py
vamb/__main__.py
vamb/_vambtools.cpython-312-darwin.so
vamb/aamb_encode.py
vamb/cluster.py
vamb/encode.py
vamb/encode_n2v_asimetric.py
vamb/git_commit.py
vamb/hloss_misc.py
vamb/kernel.npz
vamb/marker.hmm
vamb/parsebam.py
vamb/parsecontigs.py
vamb/parsemarkers.py
vamb/reclustering.py
vamb/semisupervised_encode.py
vamb/taxonomy.py
vamb/taxvamb_encode.py
vamb/vambtools.py
PlasMAAG_core-1.0.0.dist-info/LICENSE
PlasMAAG_core-1.0.0.dist-info/METADATA
PlasMAAG_core-1.0.0.dist-info/WHEEL
PlasMAAG_core-1.0.0.dist-info/entry_points.txt
PlasMAAG_core-1.0.0.dist-info/top_level.txt
PlasMAAG_core-1.0.0.dist-info/RECORD
